{
  "project_info": {
    "project_number": "838269209190",
    "project_id": "lolipet-89f42",
    "storage_bucket": "lolipet-89f42.appspot.com"
  },
  "client": [
    {
      "client_info": {
        "mobilesdk_app_id": "1:838269209190:android:19ed56aaffa6567b83fba7",
        "android_client_info": {
          "package_name": "com.example.foodorder"
        }
      },
      "oauth_client": [],
      "api_key": [
        {
          "current_key": "AIzaSyDvLRaSd6S3PJo_-EvoXPdE5BUDe_3SHZc"
        }
      ],
      "services": {
        "appinvite_service": {
          "other_platform_oauth_client": []
        }
      }
    }
  ],
  "configuration_version": "1"
}